devtools/__init__.py
devtools/main.py
geekstudio/__init__.py
geekstudio/main.py
tests/__init__.py
tests/test_main.py
geekstudio-0.0.1.dist-info/METADATA
geekstudio-0.0.1.dist-info/WHEEL
geekstudio-0.0.1.dist-info/top_level.txt
geekstudio-0.0.1.dist-info/RECORD
